easyevaluations/__init__.py
easyevaluations-1.1.dist-info/LICENSE.txt
easyevaluations-1.1.dist-info/METADATA
easyevaluations-1.1.dist-info/WHEEL
easyevaluations-1.1.dist-info/top_level.txt
easyevaluations-1.1.dist-info/RECORD
