Metadata-Version: 2.1
Name: easyevaluations
Version: 1.1
Summary: Easily evaluate the predictions of machine learning algorithms
Home-page: https://github.com/leo9226/easy_evaluations
Author: Leo Ko
Author-email: 33845@novasbe.pt
License: MIT
Download-URL: https://github.com/leo9226/easy_evaluations/archive/v1.1.tar.gz
Platform: UNKNOWN
